[
  {
	"id": "ext_repulsion_vest_spell",                                 
	"type": "SPELL",
	"name": "Energy Pulse",                                 
	"description": "A forceful explosion of energy. For the Repulsion Vest ONLY",
	"valid_targets": [ "hostile" ], 
	"effect": "attack",                                  
  "shape": "blast",                                       
	"affected_body_parts": [ "head", "torso", "mouth", "eyes", "arm_l", "arm_r", "hand_r", "hand_l", "leg_l", "foot_l", "foot_r" ],
	"flags": [ "SOMATIC", "NO_LEGS" ],
  "spell_class": "NONE",                                   
	"base_casting_time": 5,                                 
	"energy_source": "NONE",                                
	"difficulty": 0,                                        
	"max_level": 1,                                         
	"min_damage": 22,                                        
	"max_damage": 22,                                       
	"min_aoe": 3,                                           
	"max_aoe": 3,
	"min_range": 0,                                        
	"max_range": 0,
	"min_duration": 1,                                        
	"max_duration": 1,
	"damage_type": "pure",
	"sound_type": "combat",                                  
	"sound_description": "a boom",                         
	"sound_ambient": true,                                  
	"sound_id": "misc",                                      
	"sound_variant": "shockwave"                             
  },
  {
	"id": "ext_water_producer_spell",                                 
	"type": "SPELL",
	"name": "Create Water",                                 
	"description": "Makes water out of thin air. For the Water Accumulator ONLY",
	"valid_targets": [ "hostile" ], 
	"effect": "spawn_item",     
    "effect_str": "water",	
    "shape": "blast",                                       
	"flags": [ "SOMATIC", "NO_LEGS", "PERMANENT" ],
  "spell_class": "NONE",                                   
	"base_casting_time": 5,                                 
	"energy_source": "NONE",                                
	"difficulty": 0                                                          
  }
]